sandboxer/__init__.py
sandboxer/wiki_sync/__init__.py
sandboxer/wiki_sync/__main__.py
sandboxer/wiki_sync/_version.py
sandboxer/wiki_sync/cli.py
sandboxer/wiki_sync/py.typed
sandboxer/wiki_sync/core/__init__.py
sandboxer/wiki_sync/core/api.py
sandboxer/wiki_sync/core/config.py
sandboxer/wiki_sync/core/errors.py
sandboxer/wiki_sync/core/models.py
sandboxer/wiki_sync/core/sync.py
sandboxer/wiki_sync/utils/__init__.py
sandboxer/wiki_sync/utils/hashing.py
sandboxer_yandex_wiki_sync-0.1.3.dist-info/METADATA
sandboxer_yandex_wiki_sync-0.1.3.dist-info/WHEEL
sandboxer_yandex_wiki_sync-0.1.3.dist-info/entry_points.txt
sandboxer_yandex_wiki_sync-0.1.3.dist-info/licenses/LICENSE
sandboxer_yandex_wiki_sync-0.1.3.dist-info/RECORD
