Metadata-Version: 2.4
Name: sandboxer-yandex-wiki-sync
Version: 0.1.3
Summary: Sync local Markdown files with Yandex Wiki
Project-URL: Repository, https://github.com/Sandboxer-ai/sandboxer-yandex-wiki-sync
Project-URL: Documentation, https://sandboxer-ai.github.io/sandboxer-yandex-wiki-sync/
Author-email: Sandboxer AI <contact@sandboxer.ru>
License: MIT
License-File: LICENSE
Keywords: cli,markdown,sandboxer,sync,wiki,yandex
Classifier: Development Status :: 4 - Beta
Classifier: Environment :: Console
Classifier: Intended Audience :: Developers
Classifier: License :: OSI Approved :: MIT License
Classifier: Operating System :: OS Independent
Classifier: Programming Language :: Python :: 3
Classifier: Programming Language :: Python :: 3.11
Classifier: Programming Language :: Python :: 3.12
Classifier: Programming Language :: Python :: 3.13
Classifier: Programming Language :: Python :: 3.14
Classifier: Topic :: Documentation
Classifier: Topic :: Utilities
Classifier: Typing :: Typed
Requires-Python: >=3.11
Requires-Dist: pydantic-settings>=2.12.0
Requires-Dist: pydantic>=2.12.0
Requires-Dist: requests>=2.32.0
Requires-Dist: rich>=14.0.0
Requires-Dist: typer>=0.21.0
Provides-Extra: dev
Requires-Dist: bandit[toml]>=1.9.0; extra == 'dev'
Requires-Dist: mypy>=1.19.0; extra == 'dev'
Requires-Dist: pytest-cov>=7.0.0; extra == 'dev'
Requires-Dist: pytest-mock>=3.14.0; extra == 'dev'
Requires-Dist: pytest>=9.0.0; extra == 'dev'
Requires-Dist: ruff>=0.14.0; extra == 'dev'
Requires-Dist: types-requests>=2.32.0; extra == 'dev'
Requires-Dist: vulture>=2.14; extra == 'dev'
Provides-Extra: docs
Requires-Dist: mkdocs-material>=9.5; extra == 'docs'
Requires-Dist: mkdocs>=1.6; extra == 'docs'
Requires-Dist: mkdocstrings[python]>=0.27; extra == 'docs'
